simple_youtube_video_commenter/FlowFlags.py
simple_youtube_video_commenter/SimpleYoutubeVideoCommenter.py
simple_youtube_video_commenter/__init__.py
simple_youtube_video_commenter/main.py
simple_youtube_video_commenter/version.py
simple_youtube_video_commenter-1.2.6.dist-info/LICENSE
simple_youtube_video_commenter-1.2.6.dist-info/METADATA
simple_youtube_video_commenter-1.2.6.dist-info/WHEEL
simple_youtube_video_commenter-1.2.6.dist-info/entry_points.txt
simple_youtube_video_commenter-1.2.6.dist-info/top_level.txt
simple_youtube_video_commenter-1.2.6.dist-info/RECORD
