Metadata-Version: 2.1
Name: simple-youtube-video-commenter
Version: 1.2.6
Summary: CLI utility for adding comments 
Home-page: https://github.com/Koldar/simple-youtube-video-commenter
Author: Massimo Bono
Author-email: massimobono1@gmail.com
License: UNKNOWN
Platform: UNKNOWN
Classifier: Programming Language :: Python :: 3
Classifier: License :: OSI Approved :: MIT License
Classifier: Operating System :: OS Independent
Requires: setuptools
Requires: wheel
Requires-Python: >=3.6
Requires-Dist: cachetools (>=4.2.2)
Requires-Dist: certifi (>=2020.12.5)
Requires-Dist: chardet (>=4.0.0)
Requires-Dist: google-api-core (>=1.26.3)
Requires-Dist: google-api-python-client (>=2.3.0)
Requires-Dist: google-auth (>=1.30.0)
Requires-Dist: google-auth-httplib2 (>=0.1.0)
Requires-Dist: googleapis-common-protos (>=1.53.0)
Requires-Dist: httplib2 (>=0.19.1)
Requires-Dist: idna (>=2.10)
Requires-Dist: oauth2client (>=4.1.3)
Requires-Dist: packaging (>=20.9)
Requires-Dist: protobuf (>=3.15.8)
Requires-Dist: pyasn1 (>=0.4.8)
Requires-Dist: pyasn1-modules (>=0.2.8)
Requires-Dist: pyparsing (>=2.4.7)
Requires-Dist: pytz (>=2021.1)
Requires-Dist: requests (>=2.25.1)
Requires-Dist: rsa (>=4.7.2)
Requires-Dist: six (>=1.15.0)
Requires-Dist: uritemplate (>=3.0.1)
Requires-Dist: urllib3 (>=1.26.4)
Provides-Extra: doc
Provides-Extra: test
